nercst/__init__.py
nercst/core/__init__.py
nercst/core/baselinefitting.py
nercst/core/chopper_wheel.py
nercst/core/coords_converter.py
nercst/core/io.py
nercst/core/struct.py
nercst/onthefly/__init__.py
nercst/onthefly/grid.py
nercst/rsky/__init__.py
nercst/rsky/rsky.py
nercst/rsky/rsky_plot.py
nercst/skydip/__init__.py
nercst/skydip/skydip.py
nercst/skydip/slydip_plot.py
nercst/sunscan/__init__.py
nercst-0.1.6.dist-info/LICENSE
nercst-0.1.6.dist-info/METADATA
nercst-0.1.6.dist-info/WHEEL
nercst-0.1.6.dist-info/RECORD
