Metadata-Version: 2.1
Name: nercst
Version: 0.1.6
Summary: NEw reduction and calibration software for telescope 
Home-page: https://github.com/necst-telescope/NERCST
License: MIT
Author: Rin Yamada
Author-email: yamada@a.phys.nagoya-u.ac.jp
Requires-Python: >=3.8,<3.11
Classifier: License :: OSI Approved :: MIT License
Classifier: Programming Language :: Python :: 3
Classifier: Programming Language :: Python :: 3.8
Classifier: Programming Language :: Python :: 3.9
Classifier: Programming Language :: Python :: 3.10
Requires-Dist: llvmlite (>=0.39,<0.40)
Requires-Dist: matplotlib (>=3.6.2,<4.0.0)
Requires-Dist: neclib (>=0.24.2)
Requires-Dist: necstdb (>=0.2.7)
Requires-Dist: numpy (>=1.22,<2.0)
Requires-Dist: pandas (>=1.5.0,<2.0.0)
Requires-Dist: scipy (>=1.10.1,<2.0.0)
Requires-Dist: tqdm (>=4.64.1,<5.0.0)
Requires-Dist: xarray (>=2022.3,<2023.0) ; python_version >= "3.9" and python_version < "3.12"
Requires-Dist: xarray (>=2022.3,<2023.2) ; python_version >= "3.8" and python_version < "3.9"
Requires-Dist: xarray-dataclasses (>=1.3.1,<2.0.0)
Project-URL: Repository, https://github.com/necst-telescope/NERCST
